[
  {
    "web-scraper-order": "3009876543-01",
    "web-scraper-start-url": "https://sample.com/resolutions",
    "link": "2023-R01",
    "href": "https://sample.com/resolutions/2023-R01.pdf",
    "title": "A RESOLUTION SUPPORTING THE CITY'S DIGITAL TRANSFORMATION INITIATIVE TO IMPROVE PUBLIC SERVICES.",
    "author": "EMILY T. ROBLES"
  },
  {
    "web-scraper-order": "3009876543-02",
    "web-scraper-start-url": "https://sample.com/resolutions",
    "link": "2023-R02",
    "href": "https://sample.com/resolutions/2023-R02.pdf",
    "title": "A RESOLUTION RECOMMENDING THE CREATION OF MORE BIKE LANES TO PROMOTE SUSTAINABLE TRANSPORTATION.",
    "author": "GEORGE F. NAVARRO"
  },
  {
    "web-scraper-order": "3009876543-03",
    "web-scraper-start-url": "https://sample.com/resolutions",
    "link": "2023-R03",
    "href": "https://sample.com/resolutions/2023-R03.pdf",
    "title": "A RESOLUTION ENDORSING THE CONSTRUCTION OF AFFORDABLE HOUSING PROJECTS FOR LOW-INCOME RESIDENTS.",
    "author": "ISABELLE M. YAP"
  },
  {
    "web-scraper-order": "3009876543-04",
    "web-scraper-start-url": "https://sample.com/resolutions",
    "link": "2023-R04",
    "href": "https://sample.com/resolutions/2023-R04.pdf",
    "title": "A RESOLUTION ESTABLISHING A CITY-WIDE TREE PLANTING PROGRAM IN PARTNERSHIP WITH LOCAL COMMUNITIES.",
    "author": "LUIS P. VILLAR"
  },
  {
    "web-scraper-order": "3009876543-05",
    "web-scraper-start-url": "https://sample.com/resolutions",
    "link": "2023-R05",
    "href": "https://sample.com/resolutions/2023-R05.pdf",
    "title": "A RESOLUTION PROVIDING FINANCIAL AID TO SMALL BUSINESSES AFFECTED BY NATURAL DISASTERS.",
    "author": "MARIA G. SOLIS"
  },
  {
    "web-scraper-order": "3009876543-06",
    "web-scraper-start-url": "https://sample.com/resolutions",
    "link": "2023-R06",
    "href": "https://sample.com/resolutions/2023-R06.pdf",
    "title": "A RESOLUTION RECOGNIZING OUTSTANDING EDUCATORS IN THE CITY AND PROVIDING INCENTIVES.",
    "author": "FERDINAND R. LORENZO"
  },
  {
    "web-scraper-order": "3009876543-07",
    "web-scraper-start-url": "https://sample.com/resolutions",
    "link": "2023-R07",
    "href": "https://sample.com/resolutions/2023-R07.pdf",
    "title": "A RESOLUTION ENCOURAGING THE USE OF RENEWABLE ENERGY SOURCES IN GOVERNMENT BUILDINGS.",
    "author": "KAREN C. TAN"
  }
]